{
    "menu":[
        {
            "name": "Solutions", 
            "link": "0",
            "sub": [
                { "name": "Solutions By Industry", "sub": null },
                { "name": "Solutions By Process", "sub": null },
                { "name": "Software Solutions", "sub": null },
                { "name": "Services", "sub": null }
            ]
        },
        {   "name": "Products",
            "link": "1",
            "sub": [
                { "name": "Solutions By Industry PRODUCT", "sub": null },
                { "name": "Solutions By Process PRODUCT", "sub": null },
                { "name": "Software Solutions PRODUCT", "sub": null },
                { "name": "Services PRODUCT", "sub": null }
            ]
        },        
        {   "name": "Automation",
            "link": "2",
            "sub": []
        },        
        {
            "name": "Education", 
            "link": "3",
            "sub": []
        },
        {
            "name": "Resources",
            "link": "4",
            "sub": []
        }
    ]
}